soft/client/__init__.py
soft/client/__main__.py
soft/client/_userops.py
soft/client/safe.py
soft/server/__init__.py
soft/server/__main__.py
soft/server/_userops.py
soft/server/safe.py
soft_files-0.4.0.dist-info/LICENSE
soft_files-0.4.0.dist-info/WHEEL
soft_files-0.4.0.dist-info/METADATA
soft_files-0.4.0.dist-info/RECORD
